psychopy_plugin_template/__init__.py
psychopy_plugin_template/app/ribbon.py
psychopy_plugin_template/components/__init__.py
psychopy_plugin_template/components/exampleComponent/__init__.py
psychopy_plugin_template/components/exampleComponent/classic/example.png
psychopy_plugin_template/components/exampleComponent/classic/example@2x.png
psychopy_plugin_template/components/exampleComponent/dark/example.png
psychopy_plugin_template/components/exampleComponent/dark/example@2x.png
psychopy_plugin_template/components/exampleComponent/light/example.png
psychopy_plugin_template/components/exampleComponent/light/example@2x.png
psychopy_plugin_template/hardware/__init__.py
psychopy_plugin_template/hardware/exampleDevice.py
psychopy_plugin_template/hardware/exampleResponseDevice.py
psychopy_plugin_template/icons/example/__init__.py
psychopy_plugin_template/icons/example/classic/example.png
psychopy_plugin_template/icons/example/classic/example@2x.png
psychopy_plugin_template/icons/example/dark/example.png
psychopy_plugin_template/icons/example/dark/example@2x.png
psychopy_plugin_template/icons/example/light/example.png
psychopy_plugin_template/icons/example/light/example@2x.png
psychopy_plugin_template/routines/__init__.py
psychopy_plugin_template/routines/exampleStandaloneRoutine/__init__.py
psychopy_plugin_template/visual/__init__.py
psychopy_plugin_template/visual/exampleVisualStim.py
psychopy_plugin_template-0.0.5.dist-info/METADATA
psychopy_plugin_template-0.0.5.dist-info/WHEEL
psychopy_plugin_template-0.0.5.dist-info/entry_points.txt
psychopy_plugin_template-0.0.5.dist-info/top_level.txt
psychopy_plugin_template-0.0.5.dist-info/RECORD
